mkdocsplantuml/__init__.py
mkdocsplantuml/colocator.py
mkdocsplantuml/plugin.py
mkdocs_plantuml-0.1.0.dist-info/LICENSE
mkdocs_plantuml-0.1.0.dist-info/METADATA
mkdocs_plantuml-0.1.0.dist-info/WHEEL
mkdocs_plantuml-0.1.0.dist-info/entry_points.txt
mkdocs_plantuml-0.1.0.dist-info/top_level.txt
mkdocs_plantuml-0.1.0.dist-info/RECORD
