Metadata-Version: 2.1
Name: mkdocs-plantuml
Version: 0.1.0
Summary: Co-locate your plantuml source files and have them exported and linked to your techdocs
Home-page: https://github.com/NathanielWright/mkdocs-plantuml
Author: Nathaniel Wright
Author-email: nat.wright+github@gmail.com
License: MIT
Platform: UNKNOWN
License-File: LICENSE
Requires-Dist: mkdocs
